Colya/__init__.py
Colya/bot.py
Colya/setup.py
Colya/Config/__init__.py
Colya/dictionary/__init__.py
Colya/plugin/__init__.py
Colya/plugin/base.py
Colya/service/Session.py
Colya/service/WebSocket.py
Colya/service/__init__.py
Colya/service/Manager/Blueprint.py
Colya/service/Manager/__init__.py
Colya/utils/__init__.py
colya-0.3.0.dist-info/METADATA
colya-0.3.0.dist-info/WHEEL
colya-0.3.0.dist-info/top_level.txt
colya-0.3.0.dist-info/RECORD
