Metadata-Version: 2.1
Name: colya
Version: 0.3.0
Summary: A Satori QQBot Scripyt
Home-page: https://gitee.com/YSASM/ColyaBot.git
Author: Ysasm
Author-email: 1613921123@qq.com
License: MIT License
Classifier: Programming Language :: Python :: 3
